LICENSE
README.md
setup.py
kompas_scraper.egg-info/PKG-INFO
kompas_scraper.egg-info/SOURCES.txt
kompas_scraper.egg-info/dependency_links.txt
kompas_scraper.egg-info/requires.txt
kompas_scraper.egg-info/top_level.txt
pypi_scraper/__init__.py